MANIFEST.in
README.rst
setup.py
bop/__init__.py
bop/admin.py
bop/api.py
bop/backends.py
bop/decorators.py
bop/forms.py
bop/managers.py
bop/models.py
bop/urls.py
bop/views.py
bop/migrations/0001_initial.py
bop/migrations/__init__.py
bop/templatetags/__init__.py
bop/templatetags/permissions.py
bop/tests/__init__.py
bop/tests/models.py
bop/tests/tablemanager.py
django_bop.egg-info/PKG-INFO
django_bop.egg-info/SOURCES.txt
django_bop.egg-info/dependency_links.txt
django_bop.egg-info/not-zip-safe
django_bop.egg-info/top_level.txt