Metadata-Version: 1.0
Name: django-bop
Version: 0.3
Summary: Basic Object-level Permissions in django (1.2+)
Home-page: https://github.com/pterk/django-bop
Author: Peter van Kampen
Author-email: pterk@datatailors.com
License: BSD
Keywords: django object level permissions
Platform: UNKNOWN
Classifier: Development Status :: 4 - Beta
Classifier: Environment :: Web Environment
Classifier: Intended Audience :: Developers
Classifier: Operating System :: OS Independent
Classifier: Programming Language :: Python
Classifier: Framework :: Django
